[
  {
    "id": "07a2e9de-f71f-47fe-b2ef-ac98b4ab0e95",
    "data": [
      {
        "text": "cancel ",
        "userDefined": false
      },
      {
        "text": "all",
        "meta": "@sys.ignore",
        "userDefined": false
      }
    ],
    "isTemplate": false,
    "count": 0,
    "updated": 0
  },
  {
    "id": "3da4b9a1-7ce6-4a26-b1cf-70e0a363fccb",
    "data": [
      {
        "text": "skip skip skip",
        "userDefined": false
      }
    ],
    "isTemplate": false,
    "count": 0,
    "updated": 0
  },
  {
    "id": "b8847c2d-1891-47c3-93d9-12cb4b45afdc",
    "data": [
      {
        "text": "cancel that ",
        "userDefined": false
      },
      {
        "text": "one",
        "meta": "@sys.ignore",
        "userDefined": false
      }
    ],
    "isTemplate": false,
    "count": 0,
    "updated": 0
  },
  {
    "id": "9182cfe0-429f-496e-bb13-5dc0e2d06d1d",
    "data": [
      {
        "text": "cancel request",
        "userDefined": false
      }
    ],
    "isTemplate": false,
    "count": 0,
    "updated": 0
  },
  {
    "id": "2a715d77-c873-476f-be4e-c5b571e46460",
    "data": [
      {
        "text": "i said forget ",
        "userDefined": false
      },
      {
        "text": "it",
        "meta": "@sys.ignore",
        "userDefined": false
      }
    ],
    "isTemplate": false,
    "count": 0,
    "updated": 0
  },
  {
    "id": "b7c3b61e-6c6d-49ac-8e9c-42c9e875952d",
    "data": [
      {
        "text": "i would like to cancel",
        "userDefined": false
      }
    ],
    "isTemplate": false,
    "count": 0,
    "updated": 0
  },
  {
    "id": "1d2fb4dc-c17d-4459-bb0a-d68391b4cb83",
    "data": [
      {
        "text": "so cancel",
        "userDefined": false
      }
    ],
    "isTemplate": false,
    "count": 0,
    "updated": 0
  },
  {
    "id": "de7b699e-4aff-421a-93b8-b25caa5ad5b4",
    "data": [
      {
        "text": "no just cancel ",
        "userDefined": false
      },
      {
        "text": "it",
        "meta": "@sys.ignore",
        "userDefined": false
      }
    ],
    "isTemplate": false,
    "count": 0,
    "updated": 0
  },
  {
    "id": "b6009d4a-6934-495d-ad92-9f7da77fb914",
    "data": [
      {
        "text": "stop",
        "userDefined": false
      }
    ],
    "isTemplate": false,
    "count": 0,
    "updated": 0
  },
  {
    "id": "de6a3063-04e2-4b7d-9908-9765de581ea1",
    "data": [
      {
        "text": "nevermind",
        "meta": "@sys.ignore",
        "userDefined": false
      },
      {
        "text": " forget about ",
        "userDefined": false
      },
      {
        "text": "it",
        "meta": "@sys.ignore",
        "userDefined": false
      }
    ],
    "isTemplate": false,
    "count": 0,
    "updated": 0
  },
  {
    "id": "e374bccf-f48c-48d1-a391-5826384263bd",
    "data": [
      {
        "text": "disregard that",
        "userDefined": false
      }
    ],
    "isTemplate": false,
    "count": 0,
    "updated": 0
  },
  {
    "id": "bcdd37f4-020f-44a0-84d1-34934d1f57b1",
    "data": [
      {
        "text": "cancel ",
        "userDefined": false
      },
      {
        "text": "all",
        "meta": "@sys.ignore",
        "userDefined": false
      },
      {
        "text": " that",
        "userDefined": false
      }
    ],
    "isTemplate": false,
    "count": 0,
    "updated": 0
  },
  {
    "id": "01594175-229d-48a9-a9ae-510f2f698422",
    "data": [
      {
        "text": "forget this",
        "userDefined": false
      }
    ],
    "isTemplate": false,
    "count": 0,
    "updated": 0
  },
  {
    "id": "08f6dbd8-b98a-4fd2-94d1-4d820688654c",
    "data": [
      {
        "text": "no cancel cancel",
        "userDefined": false
      }
    ],
    "isTemplate": false,
    "count": 0,
    "updated": 0
  },
  {
    "id": "1711baa4-0255-4bae-9199-39cff48b722d",
    "data": [
      {
        "text": "forget",
        "userDefined": false
      }
    ],
    "isTemplate": false,
    "count": 0,
    "updated": 0
  },
  {
    "id": "449dd670-d1db-426e-92f2-e798fd8bfa02",
    "data": [
      {
        "text": "no stop",
        "userDefined": false
      }
    ],
    "isTemplate": false,
    "count": 0,
    "updated": 0
  },
  {
    "id": "86336b1e-8f2e-40f3-b3b8-55e20eda48ae",
    "data": [
      {
        "text": "just forget",
        "userDefined": false
      }
    ],
    "isTemplate": false,
    "count": 0,
    "updated": 0
  },
  {
    "id": "1c0cfa01-a2d1-4090-b5c0-b13394a17f03",
    "data": [
      {
        "text": "i said cancel ",
        "userDefined": false
      },
      {
        "text": "it",
        "meta": "@sys.ignore",
        "userDefined": false
      }
    ],
    "isTemplate": false,
    "count": 0,
    "updated": 0
  },
  {
    "id": "7b12068b-b962-4c92-bc6f-5c4414f4b002",
    "data": [
      {
        "text": "disregard",
        "userDefined": false
      }
    ],
    "isTemplate": false,
    "count": 0,
    "updated": 0
  },
  {
    "id": "246244fd-ea03-45e5-b6c3-6ea0237ceac7",
    "data": [
      {
        "text": "cancel now",
        "userDefined": false
      }
    ],
    "isTemplate": false,
    "count": 0,
    "updated": 0
  },
  {
    "id": "4d38e863-5aeb-453f-9d68-6ac658feebf7",
    "data": [
      {
        "text": "cancel",
        "userDefined": false
      }
    ],
    "isTemplate": false,
    "count": 1,
    "updated": 0
  },
  {
    "id": "f5efd91b-965e-468c-a294-d4caf455fa34",
    "data": [
      {
        "text": "cancel it",
        "userDefined": false
      }
    ],
    "isTemplate": false,
    "count": 0,
    "updated": 0
  },
  {
    "id": "53bb0cb1-978d-4973-b770-b6bb9dbea6bd",
    "data": [
      {
        "text": "do",
        "meta": "@sys.ignore",
        "userDefined": false
      },
      {
        "text": " nothing",
        "userDefined": false
      }
    ],
    "isTemplate": false,
    "count": 0,
    "updated": 0
  },
  {
    "id": "90d78a16-195c-4522-ab98-a8eac88b8830",
    "data": [
      {
        "text": "but can you cancel it",
        "userDefined": false
      }
    ],
    "isTemplate": false,
    "count": 0,
    "updated": 0
  },
  {
    "id": "a4ccfb69-83c1-4dd8-b6f5-70831517ec64",
    "data": [
      {
        "text": "cancel ",
        "userDefined": false
      },
      {
        "text": "it",
        "meta": "@sys.ignore",
        "userDefined": true
      }
    ],
    "isTemplate": false,
    "count": 0,
    "updated": 0
  },
  {
    "id": "4f6db73d-7532-4e51-a83a-3bae1ae2e3eb",
    "data": [
      {
        "text": "no just cancel",
        "userDefined": false
      }
    ],
    "isTemplate": false,
    "count": 0,
    "updated": 0
  },
  {
    "id": "8badd975-d963-4720-b4c6-ea3099d101b6",
    "data": [
      {
        "text": "forget that",
        "userDefined": false
      }
    ],
    "isTemplate": false,
    "count": 0,
    "updated": 0
  },
  {
    "id": "03d713f5-393e-44d4-abd7-8bea204eccb3",
    "data": [
      {
        "text": "cancel my request",
        "userDefined": false
      }
    ],
    "isTemplate": false,
    "count": 0,
    "updated": 0
  },
  {
    "id": "2406225f-c3ce-4e90-a6f8-150ba52a87b0",
    "data": [
      {
        "text": "cancel this request",
        "userDefined": false
      }
    ],
    "isTemplate": false,
    "count": 0,
    "updated": 0
  },
  {
    "id": "0149313a-99f7-4e4f-b020-ae61e31ea8a1",
    "data": [
      {
        "text": "stop ",
        "userDefined": false
      },
      {
        "text": "it",
        "meta": "@sys.ignore",
        "userDefined": false
      }
    ],
    "isTemplate": false,
    "count": 0,
    "updated": 0
  },
  {
    "id": "53da1cf6-52f1-4432-a0a3-fa2dea9f04ec",
    "data": [
      {
        "text": "can you cancel ",
        "userDefined": false
      },
      {
        "text": "it",
        "meta": "@sys.ignore",
        "userDefined": false
      }
    ],
    "isTemplate": false,
    "count": 0,
    "updated": 0
  },
  {
    "id": "e96122ee-5998-46cc-991e-fcccf60d5230",
    "data": [
      {
        "text": "just forget ",
        "userDefined": false
      },
      {
        "text": "it",
        "meta": "@sys.ignore",
        "userDefined": false
      }
    ],
    "isTemplate": false,
    "count": 0,
    "updated": 0
  },
  {
    "id": "04838764-0f49-4db2-97bd-a40da4ed4a7e",
    "data": [
      {
        "text": "nothing just forget ",
        "userDefined": false
      },
      {
        "text": "it",
        "meta": "@sys.ignore",
        "userDefined": false
      }
    ],
    "isTemplate": false,
    "count": 0,
    "updated": 0
  },
  {
    "id": "1f7c8adb-6cd6-45cb-bbc2-d502d4e1a13c",
    "data": [
      {
        "text": "abort",
        "userDefined": false
      }
    ],
    "isTemplate": false,
    "count": 0,
    "updated": 0
  },
  {
    "id": "e867c76c-2354-42f5-8778-44ea00ed5a53",
    "data": [
      {
        "text": "no cancel this",
        "userDefined": false
      }
    ],
    "isTemplate": false,
    "count": 0,
    "updated": 0
  },
  {
    "id": "aca0a2b2-3aa0-4909-bb40-e3682f4b1dfb",
    "data": [
      {
        "text": "forget about ",
        "userDefined": false
      },
      {
        "text": "it",
        "meta": "@sys.ignore",
        "userDefined": false
      }
    ],
    "isTemplate": false,
    "count": 0,
    "updated": 0
  },
  {
    "id": "7b87967e-7dd1-4bad-b88b-3d69eff09c23",
    "data": [
      {
        "text": "i want to cancel ",
        "userDefined": false
      },
      {
        "text": "it",
        "meta": "@sys.ignore",
        "userDefined": false
      }
    ],
    "isTemplate": false,
    "count": 0,
    "updated": 0
  },
  {
    "id": "8d1c43e1-4eae-42a3-93ec-a533dd088ffd",
    "data": [
      {
        "text": "sorry cancel",
        "userDefined": false
      }
    ],
    "isTemplate": false,
    "count": 0,
    "updated": 0
  },
  {
    "id": "fa8f084b-e4af-44fe-a224-c278fc5f035d",
    "data": [
      {
        "text": "i said cancel",
        "userDefined": false
      }
    ],
    "isTemplate": false,
    "count": 0,
    "updated": 0
  },
  {
    "id": "702c7c8d-b029-41cb-aece-b95dfc0bc38c",
    "data": [
      {
        "text": "discard",
        "userDefined": false
      }
    ],
    "isTemplate": false,
    "count": 0,
    "updated": 0
  },
  {
    "id": "73c94831-f730-4761-a8df-242170c0219f",
    "data": [
      {
        "text": "cancel that cancel that",
        "userDefined": false
      }
    ],
    "isTemplate": false,
    "count": 0,
    "updated": 0
  },
  {
    "id": "fda73fcd-2d30-42cc-9e44-15c94defcf8a",
    "data": [
      {
        "text": "I said cancel cancel",
        "userDefined": false
      }
    ],
    "isTemplate": false,
    "count": 0,
    "updated": 0
  },
  {
    "id": "a93f3d9b-be68-42e6-b614-3c63f878e93c",
    "data": [
      {
        "text": "forget about that",
        "userDefined": false
      }
    ],
    "isTemplate": false,
    "count": 0,
    "updated": 0
  },
  {
    "id": "9e10c917-9c6f-4437-a685-93f144a9d6a4",
    "data": [
      {
        "text": "skip ",
        "userDefined": false
      },
      {
        "text": "it",
        "meta": "@sys.ignore",
        "userDefined": false
      }
    ],
    "isTemplate": false,
    "count": 0,
    "updated": 0
  },
  {
    "id": "300a5cbd-ab0d-45cd-a7a2-9653e752d755",
    "data": [
      {
        "text": "no cancel everything",
        "userDefined": false
      }
    ],
    "isTemplate": false,
    "count": 0,
    "updated": 0
  },
  {
    "id": "08ba6936-329f-41ec-a41e-77fdabda4cfb",
    "data": [
      {
        "text": "cancel ",
        "userDefined": false
      },
      {
        "text": "all",
        "meta": "@sys.ignore",
        "userDefined": false
      },
      {
        "text": " this",
        "userDefined": false
      }
    ],
    "isTemplate": false,
    "count": 0,
    "updated": 0
  },
  {
    "id": "a8db4f00-1be4-4fec-9211-581e89feba45",
    "data": [
      {
        "text": "dismiss",
        "userDefined": false
      }
    ],
    "isTemplate": false,
    "count": 0,
    "updated": 0
  },
  {
    "id": "9b3594ce-c9e2-4464-8755-6ab1fd5fc4e1",
    "data": [
      {
        "text": "cancel ",
        "userDefined": false
      },
      {
        "text": "it",
        "meta": "@sys.ignore",
        "userDefined": false
      },
      {
        "text": " cancel ",
        "userDefined": false
      },
      {
        "text": "it",
        "meta": "@sys.ignore",
        "userDefined": false
      }
    ],
    "isTemplate": false,
    "count": 0,
    "updated": 0
  },
  {
    "id": "289adabf-acca-47e4-92c1-1b64b72d808d",
    "data": [
      {
        "text": "cancelled",
        "userDefined": false
      }
    ],
    "isTemplate": false,
    "count": 0,
    "updated": 0
  },
  {
    "id": "17e23d2d-a106-499e-b046-9dce1fafb0c6",
    "data": [
      {
        "text": "don\u0027t",
        "meta": "@sys.ignore",
        "userDefined": false
      },
      {
        "text": " do that",
        "userDefined": false
      }
    ],
    "isTemplate": false,
    "count": 0,
    "updated": 0
  },
  {
    "id": "89bf7d53-0ae7-4d8b-b4f5-316d996a63e5",
    "data": [
      {
        "text": "dismissed",
        "userDefined": false
      }
    ],
    "isTemplate": false,
    "count": 0,
    "updated": 0
  },
  {
    "id": "f77ae59e-4f85-4289-a555-752045080950",
    "data": [
      {
        "text": "can you cancel that",
        "userDefined": false
      }
    ],
    "isTemplate": false,
    "count": 0,
    "updated": 0
  },
  {
    "id": "7dfcee68-bc89-455d-aef5-437354d7b4f9",
    "data": [
      {
        "text": "now cancel",
        "userDefined": false
      }
    ],
    "isTemplate": false,
    "count": 0,
    "updated": 0
  },
  {
    "id": "1ec62707-1d0f-48cc-b107-790cf256aaae",
    "data": [
      {
        "text": "just cancel ",
        "userDefined": false
      },
      {
        "text": "it",
        "meta": "@sys.ignore",
        "userDefined": false
      }
    ],
    "isTemplate": false,
    "count": 0,
    "updated": 0
  },
  {
    "id": "5dad9e27-2a8f-4540-8aee-fc6d255aed51",
    "data": [
      {
        "text": "just forget about ",
        "userDefined": false
      },
      {
        "text": "it",
        "meta": "@sys.ignore",
        "userDefined": false
      }
    ],
    "isTemplate": false,
    "count": 0,
    "updated": 0
  },
  {
    "id": "3cae7a9b-244c-44c8-8eec-5542d77b00c9",
    "data": [
      {
        "text": "just stop ",
        "userDefined": false
      },
      {
        "text": "it",
        "meta": "@sys.ignore",
        "userDefined": false
      }
    ],
    "isTemplate": false,
    "count": 0,
    "updated": 0
  },
  {
    "id": "2cc9ad49-3132-458b-b949-37fe50c29242",
    "data": [
      {
        "text": "cancel the whole thing",
        "userDefined": false
      }
    ],
    "isTemplate": false,
    "count": 0,
    "updated": 0
  },
  {
    "id": "09a11e27-b78f-4cf7-94e1-dbe639aae66f",
    "data": [
      {
        "text": "i want to cancel",
        "userDefined": false
      }
    ],
    "isTemplate": false,
    "count": 0,
    "updated": 0
  },
  {
    "id": "94c0dc47-6fce-4cb0-8a95-b5b750011580",
    "data": [
      {
        "text": "skip",
        "userDefined": false
      }
    ],
    "isTemplate": false,
    "count": 1,
    "updated": 0
  },
  {
    "id": "677777b0-1cf7-48dc-8aa1-0397a67e94dc",
    "data": [
      {
        "text": "forget ",
        "userDefined": false
      },
      {
        "text": "it",
        "meta": "@sys.ignore",
        "userDefined": false
      },
      {
        "text": " ",
        "userDefined": false
      },
      {
        "text": "nevermind",
        "meta": "@sys.ignore",
        "userDefined": false
      }
    ],
    "isTemplate": false,
    "count": 0,
    "updated": 0
  },
  {
    "id": "7ea8d54f-af46-4a9f-9c8a-e9f5ab68c1a2",
    "data": [
      {
        "text": "annul",
        "userDefined": false
      }
    ],
    "isTemplate": false,
    "count": 0,
    "updated": 0
  },
  {
    "id": "0b10ced6-c6a9-4a23-ab6d-189eb472c42f",
    "data": [
      {
        "text": "nothing cancel",
        "userDefined": false
      }
    ],
    "isTemplate": false,
    "count": 0,
    "updated": 0
  },
  {
    "id": "fcfbdd7d-fca2-4846-8efc-36d017d33c90",
    "data": [
      {
        "text": "cancel everything",
        "userDefined": false
      }
    ],
    "isTemplate": false,
    "count": 0,
    "updated": 0
  }
]